jinja_layout/__init__.py
jinja_layout-0.5.0.dist-info/WHEEL
jinja_layout-0.5.0.dist-info/METADATA
jinja_layout-0.5.0.dist-info/RECORD
