Metadata-Version: 2.4
Name: jinja-layout
Version: 0.5.0
Summary: Extended layout system for Jinja
Author: Maxime Bouroumeau-Fuseau
Author-email: Maxime Bouroumeau-Fuseau <maxime.bouroumeau@gmail.com>
License-Expression: MIT
Requires-Dist: jinja2>=3.0.0,<4.0.0
Requires-Python: >=3.10
Project-URL: Repository, https://github.com/hyperflask/jinja-layout
